{
  "generatedAt": "2026-03-05T18:53:41.861Z",
  "count": 42,
  "items": [
    {
      "tmdbId": 16306,
      "title": "Fantastic Planet",
      "year": 1973,
      "reason": "ANIMATION_EXCLUDED",
      "nodeSlug": "origins-of-cult-cinema"
    },
    {
      "tmdbId": 12593,
      "title": "Fritz the Cat",
      "year": 1972,
      "reason": "ANIMATION_EXCLUDED",
      "nodeSlug": "cult-science-fiction"
    },
    {
      "tmdbId": 64847,
      "title": "Belladonna of Sadness",
      "year": 1973,
      "reason": "ANIMATION_EXCLUDED",
      "nodeSlug": "cult-science-fiction"
    },
    {
      "tmdbId": 11837,
      "title": "Watership Down",
      "year": 1978,
      "reason": "ANIMATION_EXCLUDED",
      "nodeSlug": "cult-science-fiction"
    },
    {
      "tmdbId": 11827,
      "title": "Heavy Metal",
      "year": 1981,
      "reason": "ANIMATION_EXCLUDED",
      "nodeSlug": "cult-science-fiction"
    },
    {
      "tmdbId": 10150,
      "title": "The Last Unicorn",
      "year": 1982,
      "reason": "ANIMATION_EXCLUDED",
      "nodeSlug": "cult-science-fiction"
    },
    {
      "tmdbId": 11704,
      "title": "The Secret of NIMH",
      "year": 1982,
      "reason": "ANIMATION_EXCLUDED",
      "nodeSlug": "cult-science-fiction"
    },
    {
      "tmdbId": 81,
      "title": "Nausicaä of the Valley of the Wind",
      "year": 1984,
      "reason": "ANIMATION_EXCLUDED",
      "nodeSlug": "cult-science-fiction"
    },
    {
      "tmdbId": 9463,
      "title": "Vampire Hunter D",
      "year": 1985,
      "reason": "ANIMATION_EXCLUDED",
      "nodeSlug": "cult-science-fiction"
    },
    {
      "tmdbId": 21453,
      "title": "Wicked City",
      "year": 1987,
      "reason": "ANIMATION_EXCLUDED",
      "nodeSlug": "cult-science-fiction"
    },
    {
      "tmdbId": 149,
      "title": "Akira",
      "year": 1988,
      "reason": "ANIMATION_EXCLUDED",
      "nodeSlug": "cult-science-fiction"
    },
    {
      "tmdbId": 14282,
      "title": "Ninja Scroll",
      "year": 1993,
      "reason": "ANIMATION_EXCLUDED",
      "nodeSlug": "cult-science-fiction"
    },
    {
      "tmdbId": 9323,
      "title": "Ghost in the Shell",
      "year": 1995,
      "reason": "ANIMATION_EXCLUDED",
      "nodeSlug": "cult-science-fiction"
    },
    {
      "tmdbId": 10494,
      "title": "Perfect Blue",
      "year": 1998,
      "reason": "ANIMATION_EXCLUDED",
      "nodeSlug": "cult-science-fiction"
    },
    {
      "tmdbId": 128,
      "title": "Princess Mononoke",
      "year": 1997,
      "reason": "ANIMATION_EXCLUDED",
      "nodeSlug": "cult-science-fiction"
    },
    {
      "tmdbId": 11049,
      "title": "Interstella 5555: The 5tory of the 5ecret 5tar 5ystem",
      "year": 2003,
      "reason": "ANIMATION_EXCLUDED",
      "nodeSlug": "cult-science-fiction"
    },
    {
      "tmdbId": 9389,
      "title": "Renaissance",
      "year": 2006,
      "reason": "ANIMATION_EXCLUDED",
      "nodeSlug": "cult-science-fiction"
    },
    {
      "tmdbId": 48624,
      "title": "Urotsukidōji: Legend of the Overfiend",
      "year": 1989,
      "reason": "ANIMATION_EXCLUDED",
      "nodeSlug": "video-store-era"
    },
    {
      "tmdbId": 9473,
      "title": "South Park: Bigger, Longer & Uncut",
      "year": 1999,
      "reason": "ANIMATION_EXCLUDED",
      "nodeSlug": "camp-cult-comedy"
    },
    {
      "tmdbId": 64690,
      "title": "Drive",
      "year": 2011,
      "reason": "YEAR_CAP_EXCLUDED_CURATED",
      "nodeSlug": "midnight-movies"
    },
    {
      "tmdbId": 122081,
      "title": "Spring Breakers",
      "year": 2013,
      "reason": "YEAR_CAP_EXCLUDED_CURATED",
      "nodeSlug": "midnight-movies"
    },
    {
      "tmdbId": 301365,
      "title": "The Neon Demon",
      "year": 2016,
      "reason": "YEAR_CAP_EXCLUDED_CURATED",
      "nodeSlug": "midnight-movies"
    },
    {
      "tmdbId": 435615,
      "title": "Possessor",
      "year": 2020,
      "reason": "YEAR_CAP_EXCLUDED_CURATED",
      "nodeSlug": "midnight-movies"
    },
    {
      "tmdbId": 630240,
      "title": "Titane",
      "year": 2021,
      "reason": "YEAR_CAP_EXCLUDED_CURATED",
      "nodeSlug": "midnight-movies"
    },
    {
      "tmdbId": 22970,
      "title": "The Cabin in the Woods",
      "year": 2012,
      "reason": "YEAR_CAP_EXCLUDED_CURATED",
      "nodeSlug": "midnight-movies"
    },
    {
      "tmdbId": 7025,
      "title": "It Follows",
      "year": 2014,
      "reason": "YEAR_CAP_EXCLUDED_CURATED",
      "nodeSlug": "midnight-movies"
    },
    {
      "tmdbId": 460885,
      "title": "Mandy",
      "year": 2018,
      "reason": "YEAR_CAP_EXCLUDED_CURATED",
      "nodeSlug": "midnight-movies"
    },
    {
      "tmdbId": 7029,
      "title": "Hereditary",
      "year": 2018,
      "reason": "YEAR_CAP_EXCLUDED_CURATED",
      "nodeSlug": "midnight-movies"
    },
    {
      "tmdbId": 503919,
      "title": "The Lighthouse",
      "year": 2019,
      "reason": "YEAR_CAP_EXCLUDED_CURATED",
      "nodeSlug": "midnight-movies"
    },
    {
      "tmdbId": 530385,
      "title": "Midsommar",
      "year": 2019,
      "reason": "YEAR_CAP_EXCLUDED_CURATED",
      "nodeSlug": "midnight-movies"
    },
    {
      "tmdbId": 913290,
      "title": "Barbarian",
      "year": 2022,
      "reason": "YEAR_CAP_EXCLUDED_CURATED",
      "nodeSlug": "midnight-movies"
    },
    {
      "tmdbId": 619778,
      "title": "Malignant",
      "year": 2021,
      "reason": "YEAR_CAP_EXCLUDED_CURATED",
      "nodeSlug": "midnight-movies"
    },
    {
      "tmdbId": 1201298,
      "title": "乌兰察布",
      "year": 2022,
      "reason": "YEAR_CAP_EXCLUDED_CURATED",
      "nodeSlug": "midnight-movies"
    },
    {
      "tmdbId": 667216,
      "title": "Infinity Pool",
      "year": 2023,
      "reason": "YEAR_CAP_EXCLUDED_CURATED",
      "nodeSlug": "midnight-movies"
    },
    {
      "tmdbId": 663712,
      "title": "Terrifier 2",
      "year": 2022,
      "reason": "YEAR_CAP_EXCLUDED_CURATED",
      "nodeSlug": "midnight-movies"
    },
    {
      "tmdbId": 760104,
      "title": "X",
      "year": 2022,
      "reason": "YEAR_CAP_EXCLUDED_CURATED",
      "nodeSlug": "midnight-movies"
    },
    {
      "tmdbId": 949423,
      "title": "Pearl",
      "year": 2022,
      "reason": "YEAR_CAP_EXCLUDED_CURATED",
      "nodeSlug": "midnight-movies"
    },
    {
      "tmdbId": 1520326,
      "title": "???",
      "year": 2023,
      "reason": "YEAR_CAP_EXCLUDED_CURATED",
      "nodeSlug": "midnight-movies"
    },
    {
      "tmdbId": 1008042,
      "title": "Talk to Me",
      "year": 2023,
      "reason": "YEAR_CAP_EXCLUDED_CURATED",
      "nodeSlug": "midnight-movies"
    },
    {
      "tmdbId": 241848,
      "title": "The Guest",
      "year": 2014,
      "reason": "YEAR_CAP_EXCLUDED_CURATED",
      "nodeSlug": "midnight-movies"
    },
    {
      "tmdbId": 519669,
      "title": "Можете звать меня папой",
      "year": 2016,
      "reason": "YEAR_CAP_EXCLUDED_CURATED",
      "nodeSlug": "midnight-movies"
    },
    {
      "tmdbId": 149,
      "title": "Akira",
      "year": 1988,
      "reason": "ANIMATION_EXCLUDED",
      "nodeSlug": "midnight-movies"
    }
  ]
}
